{"content": {"suites": {"0": {"status": {"total_pass": 0, "total_skip": 0, "total_xpass": 0, "total_xfail": 0, "total_rerun": 0, "total_fail": 1, "total_error": 0}, "tests": {"0": {"status": "FAIL", "message": "   selenium.common.exceptions.NoSuchElementException: Message: no such element: Unable to locate element: {\"method\":\"css selector\",\"selector\":\".start-form-check\"}\n     (Session info: chrome=120.0.6099.199); For documentation on this error, please visit: https://www.selenium.dev/documentation/webdriver/troubleshooting/errors#no-such-element-exception\n   Stacktrace:\n   0   chromedriver                        0x0000000100c144dc chromedriver + 4162780\n   1   chromedriver                        0x0000000100c0c664 chromedriver + 4130404\n   2   chromedriver                        0x0000000100863bc0 chromedriver + 293824\n   3   chromedriver                        0x00000001008aa040 chromedriver + 581696\n   4   chromedriver                        0x00000001008e9ab0 chromedriver + 842416\n   5   chromedriver                        0x000000010089d6bc chromedriver + 530108\n   6   chromedriver                        0x000000010089e930 chromedriver + 534832\n   7   chromedriver                        0x0000000100bd9e08 chromedriver + 3923464\n   8   chromedriver                        0x0000000100bde3dc chromedriver + 3941340\n   9   chromedriver                        0x0000000100bc2038 chromedriver + 3825720\n   10  chromedriver                        0x0000000100bdef3c chromedriver + 3944252\n   11  chromedriver                        0x0000000100bb46f4 chromedriver + 3770100\n   12  chromedriver                        0x0000000100bfb980 chromedriver + 4061568\n   13  chromedriver                        0x0000000100bfbaf8 chromedriver + 4061944\n   14  chromedriver                        0x0000000100c0c2e4 chromedriver + 4129508\n   15  libsystem_pthread.dylib             0x000000018a222034 _pthread_start + 136\n   16  libsystem_pthread.dylib             0x000000018a21ce3c thread_start + 8\n", "test_name": "test_add_product_rating", "rerun": "0"}}, "suite_name": "test.py"}}}, "date": "January 08, 2024", "start_time": 1704686923.0366879, "total_suite": 1, "status": "FAIL", "status_list": {"pass": "0", "fail": "1", "skip": "0", "error": "0", "xpass": "0", "xfail": "0", "rerun": "0"}, "total_tests": "1"}