{"content": {"suites": {"0": {"status": {"total_pass": 0, "total_skip": 0, "total_xpass": 0, "total_xfail": 0, "total_rerun": 0, "total_fail": 1, "total_error": 0}, "tests": {"0": {"status": "FAIL", "message": "   selenium.common.exceptions.StaleElementReferenceException: Message: stale element reference: stale element not found\n     (Session info: chrome=120.0.6099.109); For documentation on this error, please visit: https://www.selenium.dev/documentation/webdriver/troubleshooting/errors#stale-element-reference-exception\n   Stacktrace:\n   0   chromedriver                        0x00000001050984cc chromedriver + 4162764\n   1   chromedriver                        0x0000000105090654 chromedriver + 4130388\n   2   chromedriver                        0x0000000104ce7bc0 chromedriver + 293824\n   3   chromedriver                        0x0000000104cf6770 chromedriver + 354160\n   4   chromedriver                        0x0000000104cedaf0 chromedriver + 318192\n   5   chromedriver                        0x0000000104cedbc8 chromedriver + 318408\n   6   chromedriver                        0x0000000104cec17c chromedriver + 311676\n   7   chromedriver                        0x0000000104cef4d0 chromedriver + 324816\n   8   chromedriver                        0x0000000104d6e46c chromedriver + 844908\n   9   chromedriver                        0x0000000104d6dab0 chromedriver + 842416\n   10  chromedriver                        0x0000000104d216bc chromedriver + 530108\n   11  chromedriver                        0x0000000104d22930 chromedriver + 534832\n   12  chromedriver                        0x000000010505ddf8 chromedriver + 3923448\n   13  chromedriver                        0x00000001050623cc chromedriver + 3941324\n   14  chromedriver                        0x0000000105046028 chromedriver + 3825704\n   15  chromedriver                        0x0000000105062f2c chromedriver + 3944236\n   16  chromedriver                        0x00000001050386e4 chromedriver + 3770084\n   17  chromedriver                        0x000000010507f970 chromedriver + 4061552\n   18  chromedriver                        0x000000010507fae8 chromedriver + 4061928\n   19  chromedriver                        0x00000001050902d4 chromedriver + 4129492\n   20  libsystem_pthread.dylib             0x0000000182bf9034 _pthread_start + 136\n   21  libsystem_pthread.dylib             0x0000000182bf3e3c thread_start + 8\n", "test_name": "test_edit_user", "rerun": "0"}}, "suite_name": "tests/04-edit_user_test/test_edit_user.py"}}}, "date": "December 16, 2023", "start_time": 1702707039.998996, "total_suite": 1, "status": "FAIL", "status_list": {"pass": "0", "fail": "1", "skip": "0", "error": "0", "xpass": "0", "xfail": "0", "rerun": "0"}, "total_tests": "1"}